crawlerlib/__init__.py
crawlerlib/chrome_extension.py
crawlerlib/html.py
crawlerlib/re.py
crawlerlib/tools.py
crawlerlib/url.py
crawlerlib-0.1.0.dist-info/LICENSE
crawlerlib-0.1.0.dist-info/METADATA
crawlerlib-0.1.0.dist-info/WHEEL
crawlerlib-0.1.0.dist-info/RECORD
