Metadata-Version: 2.1
Name: crawlerlib
Version: 0.1.0
Summary: 
Author: mathewgeola
Author-email: mathewgeola@163.com
Requires-Python: >=3.10,<4.0
Classifier: Programming Language :: Python :: 3
Classifier: Programming Language :: Python :: 3.10
Classifier: Programming Language :: Python :: 3.11
Classifier: Programming Language :: Python :: 3.12
Requires-Dist: furl (>=2.1.3,<3.0.0)
Requires-Dist: htmlmin (>=0.1.12,<0.2.0)
